LICENSE
README.rst
setup.cfg
setup.py
pyforwind/__init__.py
pyforwind/aux.py
pyforwind/pyforwind.py
pyforwind/pyforwind_copy.py
pyforwind/pyforwind_corrected.py
pyforwind/pyforwind_corrected_spec.py
pyforwind/pyforwind_mann.py
pyforwind/pyforwind_spatiotemporal.py
pyforwind/pyforwind_wake.py
pyforwind/wind_fields_3D.py
pyforwind.egg-info/PKG-INFO
pyforwind.egg-info/SOURCES.txt
pyforwind.egg-info/dependency_links.txt
pyforwind.egg-info/entry_points.txt
pyforwind.egg-info/requires.txt
pyforwind.egg-info/top_level.txt