Metadata-Version: 2.1
Name: pyforwind
Version: 0.1.3
Summary: Synthetic IEC-conform wind fields with extended turbulence characteristics
Home-page: https://github.com/fiddir/pyforwind
Maintainer: Jan Friedrich
License: LGPL-3.0
Keywords: synthetic wind fields,inflow turbulence,wind energy
Platform: any
License-File: LICENSE
Requires-Dist: requests
Requires-Dist: scipy
Requires-Dist: numpy
Requires-Dist: matplotlib
Requires-Dist: pandas
